setup.py
decogres/__init__.py
decogres/decorator.py
decogres/postgresql.py
decogres.egg-info/PKG-INFO
decogres.egg-info/SOURCES.txt
decogres.egg-info/dependency_links.txt
decogres.egg-info/requires.txt
decogres.egg-info/top_level.txt