Metadata-Version: 1.1
Name: decogres
Version: 1.0.5
Summary: Postgresql decorator
Home-page: https://github.com/hfukada/py-decogres
Author: Hiroshi Fukada
Author-email: hiroshi@fukada.us
License: UNKNOWN
Download-URL: https://github.com/hfukada/py-decogres/tarball/1.0.5
Platform: UNKNOWN
